{
  "generatedAt": "2026-06-29T12:35:26.466779+00:00",
  "timePeriod": "WEEK",
  "bankroll": 100.0,
  "tradersChecked": 92,
  "categoryBreakdown": {
    "OVERALL": 50,
    "CRYPTO": 20,
    "POLITICS": 22
  },
  "positionsScanned": 719,
  "opportunities": [
    {
      "title": "Wimbledon WTA: Elsa Jacquemot vs Naomi Osaka",
      "outcome": "Naomi Osaka",
      "slug": "wta-jacquem-osaka-2026-06-29",
      "url": "https://polymarket.com/event/wta-jacquem-osaka-2026-06-29",
      "curPrice": 0.845,
      "estimatedEdge": 0.0611,
      "kellyBet": 9.85,
      "kellyFull": 0.394,
      "nSmartTraders": 2,
      "totalTradersChecked": 92,
      "smartTraderNames": [
        "swisstony",
        "0x076daa..."
      ],
      "countSignal": 0.0119,
      "sizeSignal": 1.0,
      "totalExposure": 23937.27,
      "weightedAvgEntry": 0.8639
    },
    {
      "title": "Will Bitcoin dip to $30,000 by December 31, 2026?",
      "outcome": "No",
      "slug": "will-bitcoin-dip-to-30000-by-december-31-2026-971-191-116-343-999-758-299",
      "url": "https://polymarket.com/event/will-bitcoin-dip-to-30000-by-december-31-2026-971-191-116-343-999-758-299",
      "curPrice": 0.885,
      "estimatedEdge": 0.0439,
      "kellyBet": 9.55,
      "kellyFull": 0.3819,
      "nSmartTraders": 2,
      "totalTradersChecked": 92,
      "smartTraderNames": [
        "JnStTrdrBnusFnd",
        "justdance"
      ],
      "countSignal": 0.0176,
      "sizeSignal": 1.0,
      "totalExposure": 53472.26,
      "weightedAvgEntry": 0.8563
    },
    {
      "title": "Will there be no change in Fed interest rates after the July 2026 meeting?",
      "outcome": "Yes",
      "slug": "will-there-be-no-change-in-fed-interest-rates-after-the-july-2026-meeting",
      "url": "https://polymarket.com/event/will-there-be-no-change-in-fed-interest-rates-after-the-july-2026-meeting",
      "curPrice": 0.8149,
      "estimatedEdge": 0.0632,
      "kellyBet": 8.53,
      "kellyFull": 0.3412,
      "nSmartTraders": 2,
      "totalTradersChecked": 92,
      "smartTraderNames": [
        "NonceChaser",
        "Valen9"
      ],
      "countSignal": 0.1229,
      "sizeSignal": 1.0,
      "totalExposure": 29869.87,
      "weightedAvgEntry": 0.8038
    },
    {
      "title": "Will Japan win on 2026-06-29?",
      "outcome": "No",
      "slug": "fifwc-bra-jpn-2026-06-29-jpn",
      "url": "https://polymarket.com/event/fifwc-bra-jpn-2026-06-29-jpn",
      "curPrice": 0.825,
      "estimatedEdge": 0.0586,
      "kellyBet": 8.37,
      "kellyFull": 0.3348,
      "nSmartTraders": 3,
      "totalTradersChecked": 92,
      "smartTraderNames": [
        "BreakTheBank",
        "swisstony",
        "0x076daa..."
      ],
      "countSignal": 0.0177,
      "sizeSignal": 1.0,
      "totalExposure": 518077.22,
      "weightedAvgEntry": 0.8201
    },
    {
      "title": "Will the Republican Party control the House after the 2026 Midterm elections?",
      "outcome": "No",
      "slug": "will-the-republican-party-control-the-house-after-the-2026-midterm-elections",
      "url": "https://polymarket.com/event/will-the-republican-party-control-the-house-after-the-2026-midterm-elections",
      "curPrice": 0.825,
      "estimatedEdge": 0.0565,
      "kellyBet": 8.08,
      "kellyFull": 0.3231,
      "nSmartTraders": 2,
      "totalTradersChecked": 92,
      "smartTraderNames": [
        "Valen9",
        "debased"
      ],
      "countSignal": 0.0267,
      "sizeSignal": 1.0,
      "totalExposure": 20951.28,
      "weightedAvgEntry": 0.8156
    },
    {
      "title": "Will Argentina win the 2026 FIFA World Cup?",
      "outcome": "No",
      "slug": "will-argentina-win-the-2026-fifa-world-cup-245",
      "url": "https://polymarket.com/event/will-argentina-win-the-2026-fifa-world-cup-245",
      "curPrice": 0.7915,
      "estimatedEdge": 0.0636,
      "kellyBet": 7.62,
      "kellyFull": 0.3048,
      "nSmartTraders": 2,
      "totalTradersChecked": 92,
      "smartTraderNames": [
        "S-Works",
        "Valen9"
      ],
      "countSignal": 0.0396,
      "sizeSignal": 1.0,
      "totalExposure": 210032.89,
      "weightedAvgEntry": 0.8805
    },
    {
      "title": "US-Iran Final Nuclear Deal by August 31, 2026?",
      "outcome": "No",
      "slug": "us-iran-final-nuclear-deal-by-august-31-2026-20260621201255154",
      "url": "https://polymarket.com/event/us-iran-final-nuclear-deal-by-august-31-2026-20260621201255154",
      "curPrice": 0.765,
      "estimatedEdge": 0.0545,
      "kellyBet": 5.8,
      "kellyFull": 0.232,
      "nSmartTraders": 2,
      "totalTradersChecked": 92,
      "smartTraderNames": [
        "timmythewhale",
        "NonceChaser"
      ],
      "countSignal": 0.1089,
      "sizeSignal": 1.0,
      "totalExposure": 22185.0,
      "weightedAvgEntry": 0.7431
    },
    {
      "title": "Will Germany win on 2026-06-29?",
      "outcome": "Yes",
      "slug": "fifwc-ger-par-2026-06-29-ger",
      "url": "https://polymarket.com/event/fifwc-ger-par-2026-06-29-ger",
      "curPrice": 0.725,
      "estimatedEdge": 0.0624,
      "kellyBet": 5.68,
      "kellyFull": 0.227,
      "nSmartTraders": 2,
      "totalTradersChecked": 92,
      "smartTraderNames": [
        "0x3DA89a55CdD4b5c69F80E5Cd3ef1782a3E0480c3-1777119032461",
        "tm877"
      ],
      "countSignal": 0.0271,
      "sizeSignal": 1.0,
      "totalExposure": 5110.75,
      "weightedAvgEntry": 0.7296
    },
    {
      "title": "Will Bitcoin dip to $40,000 by December 31, 2026?",
      "outcome": "No",
      "slug": "will-bitcoin-dip-to-40000-by-december-31-2026-593-522-842-874-931-776-991-167",
      "url": "https://polymarket.com/event/will-bitcoin-dip-to-40000-by-december-31-2026-593-522-842-874-931-776-991-167",
      "curPrice": 0.725,
      "estimatedEdge": 0.0616,
      "kellyBet": 5.6,
      "kellyFull": 0.2239,
      "nSmartTraders": 2,
      "totalTradersChecked": 92,
      "smartTraderNames": [
        "JnStTrdrBnusFnd",
        "justdance"
      ],
      "countSignal": 0.0176,
      "sizeSignal": 1.0,
      "totalExposure": 90354.53,
      "weightedAvgEntry": 0.7507
    },
    {
      "title": "Will United States win on 2026-07-01?",
      "outcome": "Yes",
      "slug": "fifwc-usa-bih-2026-07-01-usa",
      "url": "https://polymarket.com/event/fifwc-usa-bih-2026-07-01-usa",
      "curPrice": 0.715,
      "estimatedEdge": 0.0614,
      "kellyBet": 5.38,
      "kellyFull": 0.2153,
      "nSmartTraders": 3,
      "totalTradersChecked": 92,
      "smartTraderNames": [
        "swisstony",
        "wr0ngw4yb3tt0r",
        "0x3DA89a55CdD4b5c69F80E5Cd3ef1782a3E0480c3-1777119032461"
      ],
      "countSignal": 0.0151,
      "sizeSignal": 1.0,
      "totalExposure": 83662.13,
      "weightedAvgEntry": 0.7191
    },
    {
      "title": "Wimbledon ATP: Michael Zheng vs Cameron Norrie",
      "outcome": "Cameron Norrie",
      "slug": "atp-zheng-norrie-2026-06-29",
      "url": "https://polymarket.com/event/atp-zheng-norrie-2026-06-29",
      "curPrice": 0.675,
      "estimatedEdge": 0.0692,
      "kellyBet": 5.33,
      "kellyFull": 0.213,
      "nSmartTraders": 3,
      "totalTradersChecked": 92,
      "smartTraderNames": [
        "ferrariChampions2026",
        "RN1",
        "0x076daa..."
      ],
      "countSignal": 0.1026,
      "sizeSignal": 1.0,
      "totalExposure": 76831.62,
      "weightedAvgEntry": 0.7461
    },
    {
      "title": "Will Ecuador win on 2026-06-30?",
      "outcome": "No",
      "slug": "fifwc-mex-ecu-2026-06-30-ecu",
      "url": "https://polymarket.com/event/fifwc-mex-ecu-2026-06-30-ecu",
      "curPrice": 0.765,
      "estimatedEdge": 0.0484,
      "kellyBet": 5.15,
      "kellyFull": 0.2059,
      "nSmartTraders": 2,
      "totalTradersChecked": 92,
      "smartTraderNames": [
        "swisstony",
        "wr0ngw4yb3tt0r"
      ],
      "countSignal": 0.0134,
      "sizeSignal": 1.0,
      "totalExposure": 39439.37,
      "weightedAvgEntry": 0.744
    },
    {
      "title": "Bitcoin Up or Down - June 29, 8:30AM-8:35AM ET",
      "outcome": "Down",
      "slug": "btc-updown-5m-1782736200",
      "url": "https://polymarket.com/event/btc-updown-5m-1782736200",
      "curPrice": 0.645,
      "estimatedEdge": 0.0723,
      "kellyBet": 5.09,
      "kellyFull": 0.2036,
      "nSmartTraders": 5,
      "totalTradersChecked": 92,
      "smartTraderNames": [
        "Bonereaper",
        "0xb27bc9...",
        "Xieyt",
        "0x13e0d4...",
        "baloneigh"
      ],
      "countSignal": 0.1362,
      "sizeSignal": 1.0,
      "totalExposure": 6541.81,
      "weightedAvgEntry": 0.6786
    },
    {
      "title": "Spread: Brazil (-1.5)",
      "outcome": "Japan",
      "slug": "fifwc-bra-jpn-2026-06-29-spread-home-1pt5",
      "url": "https://polymarket.com/event/fifwc-bra-jpn-2026-06-29-spread-home-1pt5",
      "curPrice": 0.705,
      "estimatedEdge": 0.0564,
      "kellyBet": 4.78,
      "kellyFull": 0.1912,
      "nSmartTraders": 2,
      "totalTradersChecked": 92,
      "smartTraderNames": [
        "swisstony",
        "wr0ngw4yb3tt0r"
      ],
      "countSignal": 0.0134,
      "sizeSignal": 1.0,
      "totalExposure": 146244.03,
      "weightedAvgEntry": 0.6972
    },
    {
      "title": "Spread: Germany (-2.5)",
      "outcome": "Paraguay",
      "slug": "fifwc-ger-par-2026-06-29-spread-home-2pt5",
      "url": "https://polymarket.com/event/fifwc-ger-par-2026-06-29-spread-home-2pt5",
      "curPrice": 0.755,
      "estimatedEdge": 0.0452,
      "kellyBet": 4.61,
      "kellyFull": 0.1844,
      "nSmartTraders": 2,
      "totalTradersChecked": 92,
      "smartTraderNames": [
        "0x076daa...",
        "wr0ngw4yb3tt0r"
      ],
      "countSignal": 0.0035,
      "sizeSignal": 1.0,
      "totalExposure": 6214.56,
      "weightedAvgEntry": 0.7299
    },
    {
      "title": "Katy Perry and Justin Trudeau engaged by end of 2026?",
      "outcome": "No",
      "slug": "katy-perry-and-justin-trudeau-engaged-by-end-of-2026",
      "url": "https://polymarket.com/event/katy-perry-and-justin-trudeau-engaged-by-end-of-2026",
      "curPrice": 0.635,
      "estimatedEdge": 0.0632,
      "kellyBet": 4.33,
      "kellyFull": 0.173,
      "nSmartTraders": 2,
      "totalTradersChecked": 92,
      "smartTraderNames": [
        "Valen9",
        "Bertapotamous"
      ],
      "countSignal": 0.035,
      "sizeSignal": 1.0,
      "totalExposure": 1730.91,
      "weightedAvgEntry": 0.7509
    },
    {
      "title": "Wimbledon ATP: Soon-Woo Kwon vs Martin Landaluce",
      "outcome": "Martin Landaluce",
      "slug": "atp-kwon-landalu-2026-06-29",
      "url": "https://polymarket.com/event/atp-kwon-landalu-2026-06-29",
      "curPrice": 0.605,
      "estimatedEdge": 0.0674,
      "kellyBet": 4.26,
      "kellyFull": 0.1706,
      "nSmartTraders": 2,
      "totalTradersChecked": 92,
      "smartTraderNames": [
        "0x076daa...",
        "ferrariChampions2026"
      ],
      "countSignal": 0.082,
      "sizeSignal": 1.0,
      "totalExposure": 2508.67,
      "weightedAvgEntry": 0.6053
    },
    {
      "title": "Will Mike Mazzei win the 2026 Oklahoma Governor Republican primary election?",
      "outcome": "Yes",
      "slug": "will-mike-mazzei-win-the-2026-oklahoma-governor-republican-primary-election",
      "url": "https://polymarket.com/event/will-mike-mazzei-win-the-2026-oklahoma-governor-republican-primary-election",
      "curPrice": 0.7915,
      "estimatedEdge": 0.0342,
      "kellyBet": 4.1,
      "kellyFull": 0.1641,
      "nSmartTraders": 2,
      "totalTradersChecked": 92,
      "smartTraderNames": [
        "mombil",
        "Bertapotamous"
      ],
      "countSignal": 0.0231,
      "sizeSignal": 1.0,
      "totalExposure": 2703.47,
      "weightedAvgEntry": 0.7466
    },
    {
      "title": "Spread: Argentina (-1.5)",
      "outcome": "Argentina",
      "slug": "fifwc-arg-cvi-2026-07-03-spread-home-1pt5",
      "url": "https://polymarket.com/event/fifwc-arg-cvi-2026-07-03-spread-home-1pt5",
      "curPrice": 0.615,
      "estimatedEdge": 0.0631,
      "kellyBet": 4.1,
      "kellyFull": 0.1638,
      "nSmartTraders": 3,
      "totalTradersChecked": 92,
      "smartTraderNames": [
        "swisstony",
        "RN1",
        "wr0ngw4yb3tt0r"
      ],
      "countSignal": 0.034,
      "sizeSignal": 1.0,
      "totalExposure": 56363.01,
      "weightedAvgEntry": 0.6236
    },
    {
      "title": "Will Bitcoin dip to $45,000 by December 31, 2026?",
      "outcome": "No",
      "slug": "will-bitcoin-dip-to-45000-by-december-31-2026-674-923-755-971-998-525-926-245-316-517-544-589-965-923-986-841-815-224-586-231-289",
      "url": "https://polymarket.com/event/will-bitcoin-dip-to-45000-by-december-31-2026-674-923-755-971-998-525-926-245-316-517-544-589-965-923-986-841-815-224-586-231-289",
      "curPrice": 0.555,
      "estimatedEdge": 0.0623,
      "kellyBet": 3.5,
      "kellyFull": 0.14,
      "nSmartTraders": 3,
      "totalTradersChecked": 92,
      "smartTraderNames": [
        "JnStTrdrBnusFnd",
        "oegdatam",
        "justdance"
      ],
      "countSignal": 0.0255,
      "sizeSignal": 1.0,
      "totalExposure": 131084.31,
      "weightedAvgEntry": 0.6939
    },
    {
      "title": "Will Mexico win on 2026-06-30?",
      "outcome": "No",
      "slug": "fifwc-mex-ecu-2026-06-30-mex",
      "url": "https://polymarket.com/event/fifwc-mex-ecu-2026-06-30-mex",
      "curPrice": 0.555,
      "estimatedEdge": 0.0613,
      "kellyBet": 3.44,
      "kellyFull": 0.1377,
      "nSmartTraders": 3,
      "totalTradersChecked": 92,
      "smartTraderNames": [
        "swisstony",
        "0x076daa...",
        "wr0ngw4yb3tt0r"
      ],
      "countSignal": 0.0144,
      "sizeSignal": 1.0,
      "totalExposure": 35107.98,
      "weightedAvgEntry": 0.5613
    },
    {
      "title": "Will Brazil win on 2026-06-29?",
      "outcome": "Yes",
      "slug": "fifwc-bra-jpn-2026-06-29-bra",
      "url": "https://polymarket.com/event/fifwc-bra-jpn-2026-06-29-bra",
      "curPrice": 0.5649,
      "estimatedEdge": 0.0597,
      "kellyBet": 3.43,
      "kellyFull": 0.1373,
      "nSmartTraders": 2,
      "totalTradersChecked": 92,
      "smartTraderNames": [
        "BreakTheBank",
        "tm877"
      ],
      "countSignal": 0.0312,
      "sizeSignal": 1.0,
      "totalExposure": 68104.89,
      "weightedAvgEntry": 0.56
    },
    {
      "title": "Fed rate hike in 2026?",
      "outcome": "Yes",
      "slug": "fed-rate-hike-in-2026",
      "url": "https://polymarket.com/event/fed-rate-hike-in-2026",
      "curPrice": 0.525,
      "estimatedEdge": 0.063,
      "kellyBet": 3.31,
      "kellyFull": 0.1326,
      "nSmartTraders": 3,
      "totalTradersChecked": 92,
      "smartTraderNames": [
        "Valen9",
        "Gengfrauds",
        "back-in-whack"
      ],
      "countSignal": 0.0331,
      "sizeSignal": 1.0,
      "totalExposure": 9891.96,
      "weightedAvgEntry": 0.633
    },
    {
      "title": "Tampa Bay Rays vs. Boston Red Sox",
      "outcome": "Boston Red Sox",
      "slug": "mlb-tb-bos-2026-05-09",
      "url": "https://polymarket.com/event/mlb-tb-bos-2026-05-09",
      "curPrice": 0.475,
      "estimatedEdge": 0.0691,
      "kellyBet": 3.29,
      "kellyFull": 0.1317,
      "nSmartTraders": 2,
      "totalTradersChecked": 92,
      "smartTraderNames": [
        "ferrariChampions2026",
        "RN1"
      ],
      "countSignal": 0.1016,
      "sizeSignal": 1.0,
      "totalExposure": 76918.85,
      "weightedAvgEntry": 0.5561
    },
    {
      "title": "Wimbledon ATP: Marco Trungelliti vs Martin Damm",
      "outcome": "Martin Damm",
      "slug": "atp-trungel-damm-2026-06-29",
      "url": "https://polymarket.com/event/atp-trungel-damm-2026-06-29",
      "curPrice": 0.465,
      "estimatedEdge": 0.0691,
      "kellyBet": 3.23,
      "kellyFull": 0.1292,
      "nSmartTraders": 2,
      "totalTradersChecked": 92,
      "smartTraderNames": [
        "ferrariChampions2026",
        "RN1"
      ],
      "countSignal": 0.1016,
      "sizeSignal": 1.0,
      "totalExposure": 24897.07,
      "weightedAvgEntry": 0.6972
    },
    {
      "title": "Will Norway win on 2026-06-30?",
      "outcome": "No",
      "slug": "fifwc-civ-nor-2026-06-30-nor",
      "url": "https://polymarket.com/event/fifwc-civ-nor-2026-06-30-nor",
      "curPrice": 0.525,
      "estimatedEdge": 0.0608,
      "kellyBet": 3.2,
      "kellyFull": 0.1281,
      "nSmartTraders": 3,
      "totalTradersChecked": 92,
      "smartTraderNames": [
        "0x076daa...",
        "swisstony",
        "wr0ngw4yb3tt0r"
      ],
      "countSignal": 0.0144,
      "sizeSignal": 1.0,
      "totalExposure": 168631.98,
      "weightedAvgEntry": 0.5243
    },
    {
      "title": "Wimbledon ATP: Camilo Ugo Carabelli vs Daniel Merida Aguilar",
      "outcome": "Daniel Merida Aguilar",
      "slug": "atp-carabel-aguilar-2026-06-29",
      "url": "https://polymarket.com/event/atp-carabel-aguilar-2026-06-29",
      "curPrice": 0.445,
      "estimatedEdge": 0.0692,
      "kellyBet": 3.12,
      "kellyFull": 0.1247,
      "nSmartTraders": 3,
      "totalTradersChecked": 92,
      "smartTraderNames": [
        "ferrariChampions2026",
        "0x076daa...",
        "RN1"
      ],
      "countSignal": 0.1026,
      "sizeSignal": 1.0,
      "totalExposure": 5813.89,
      "weightedAvgEntry": 0.5157
    },
    {
      "title": "Boston Red Sox vs. New York Yankees",
      "outcome": "New York Yankees",
      "slug": "mlb-bos-nyy-2026-06-06",
      "url": "https://polymarket.com/event/mlb-bos-nyy-2026-06-06",
      "curPrice": 0.49,
      "estimatedEdge": 0.0622,
      "kellyBet": 3.05,
      "kellyFull": 0.122,
      "nSmartTraders": 3,
      "totalTradersChecked": 92,
      "smartTraderNames": [
        "wr0ngw4yb3tt0r",
        "RN1",
        "0x3DA89a55CdD4b5c69F80E5Cd3ef1782a3E0480c3-1777119032461"
      ],
      "countSignal": 0.0247,
      "sizeSignal": 1.0,
      "totalExposure": 10668.02,
      "weightedAvgEntry": 0.5
    },
    {
      "title": "Wimbledon WTA: Mananchaya Sawangkaew vs Maja Chwalinska",
      "outcome": "Maja Chwalinska",
      "slug": "wta-sawangk-chwalin-2026-06-29",
      "url": "https://polymarket.com/event/wta-sawangk-chwalin-2026-06-29",
      "curPrice": 0.381,
      "estimatedEdge": 0.0733,
      "kellyBet": 2.96,
      "kellyFull": 0.1183,
      "nSmartTraders": 5,
      "totalTradersChecked": 92,
      "smartTraderNames": [
        "0x594d0c...",
        "RN1",
        "ferrariChampions2026",
        "letitride247",
        "0x076daa..."
      ],
      "countSignal": 0.1473,
      "sizeSignal": 1.0,
      "totalExposure": 114099.56,
      "weightedAvgEntry": 0.6255
    },
    {
      "title": "Spread: Germany (-1.5)",
      "outcome": "Germany",
      "slug": "fifwc-ger-par-2026-06-29-spread-home-1pt5",
      "url": "https://polymarket.com/event/fifwc-ger-par-2026-06-29-spread-home-1pt5",
      "curPrice": 0.455,
      "estimatedEdge": 0.062,
      "kellyBet": 2.84,
      "kellyFull": 0.1138,
      "nSmartTraders": 4,
      "totalTradersChecked": 92,
      "smartTraderNames": [
        "swisstony",
        "0x076daa...",
        "wr0ngw4yb3tt0r",
        "Gambleguy123"
      ],
      "countSignal": 0.0224,
      "sizeSignal": 1.0,
      "totalExposure": 123013.37,
      "weightedAvgEntry": 0.4679
    },
    {
      "title": "Germany vs. Paraguay: O/U 2.5",
      "outcome": "Under",
      "slug": "fifwc-ger-par-2026-06-29-total-2pt5",
      "url": "https://polymarket.com/event/fifwc-ger-par-2026-06-29-total-2pt5",
      "curPrice": 0.435,
      "estimatedEdge": 0.0607,
      "kellyBet": 2.69,
      "kellyFull": 0.1075,
      "nSmartTraders": 2,
      "totalTradersChecked": 92,
      "smartTraderNames": [
        "swisstony",
        "0x076daa..."
      ],
      "countSignal": 0.0119,
      "sizeSignal": 1.0,
      "totalExposure": 91736.39,
      "weightedAvgEntry": 0.4345
    },
    {
      "title": "Spread: France (-1.5)",
      "outcome": "Sweden",
      "slug": "fifwc-fra-swe-2026-06-30-spread-home-1pt5",
      "url": "https://polymarket.com/event/fifwc-fra-swe-2026-06-30-spread-home-1pt5",
      "curPrice": 0.445,
      "estimatedEdge": 0.0592,
      "kellyBet": 2.67,
      "kellyFull": 0.1067,
      "nSmartTraders": 3,
      "totalTradersChecked": 92,
      "smartTraderNames": [
        "wr0ngw4yb3tt0r",
        "0x076daa...",
        "swisstony"
      ],
      "countSignal": 0.0144,
      "sizeSignal": 1.0,
      "totalExposure": 190454.42,
      "weightedAvgEntry": 0.4416
    },
    {
      "title": "Brazil vs. Japan: O/U 2.5",
      "outcome": "Over",
      "slug": "fifwc-bra-jpn-2026-06-29-total-2pt5",
      "url": "https://polymarket.com/event/fifwc-bra-jpn-2026-06-29-total-2pt5",
      "curPrice": 0.455,
      "estimatedEdge": 0.0576,
      "kellyBet": 2.64,
      "kellyFull": 0.1057,
      "nSmartTraders": 2,
      "totalTradersChecked": 92,
      "smartTraderNames": [
        "swisstony",
        "RN1"
      ],
      "countSignal": 0.0315,
      "sizeSignal": 1.0,
      "totalExposure": 122636.41,
      "weightedAvgEntry": 0.4467
    },
    {
      "title": "Strait of Hormuz traffic returns to normal by July 31?",
      "outcome": "Yes",
      "slug": "strait-of-hormuz-traffic-returns-to-normal-by-july-31",
      "url": "https://polymarket.com/event/strait-of-hormuz-traffic-returns-to-normal-by-july-31",
      "curPrice": 0.385,
      "estimatedEdge": 0.0645,
      "kellyBet": 2.62,
      "kellyFull": 0.1048,
      "nSmartTraders": 2,
      "totalTradersChecked": 92,
      "smartTraderNames": [
        "mombil",
        "deltasniper"
      ],
      "countSignal": 0.0497,
      "sizeSignal": 1.0,
      "totalExposure": 9047.5,
      "weightedAvgEntry": 0.4633
    },
    {
      "title": "Will Brazil win on 2026-06-29?",
      "outcome": "No",
      "slug": "fifwc-bra-jpn-2026-06-29-bra",
      "url": "https://polymarket.com/event/fifwc-bra-jpn-2026-06-29-bra",
      "curPrice": 0.435,
      "estimatedEdge": 0.0591,
      "kellyBet": 2.61,
      "kellyFull": 0.1045,
      "nSmartTraders": 6,
      "totalTradersChecked": 92,
      "smartTraderNames": [
        "BreakTheBank",
        "wr0ngw4yb3tt0r",
        "swisstony",
        "0x076daa...",
        "RN1"
      ],
      "countSignal": 0.0722,
      "sizeSignal": 1.0,
      "totalExposure": 644106.99,
      "weightedAvgEntry": 0.4238
    },
    {
      "title": "Spread: Argentina (-2.5)",
      "outcome": "Argentina",
      "slug": "fifwc-arg-cvi-2026-07-03-spread-home-2pt5",
      "url": "https://polymarket.com/event/fifwc-arg-cvi-2026-07-03-spread-home-2pt5",
      "curPrice": 0.375,
      "estimatedEdge": 0.0628,
      "kellyBet": 2.51,
      "kellyFull": 0.1005,
      "nSmartTraders": 2,
      "totalTradersChecked": 92,
      "smartTraderNames": [
        "swisstony",
        "RN1"
      ],
      "countSignal": 0.0315,
      "sizeSignal": 1.0,
      "totalExposure": 20998.24,
      "weightedAvgEntry": 0.3862
    },
    {
      "title": "Will Bitcoin dip to $50,000 by December 31, 2026?",
      "outcome": "No",
      "slug": "will-bitcoin-dip-to-50000-by-december-31-2026-454-325-222-878-949-487-451-853",
      "url": "https://polymarket.com/event/will-bitcoin-dip-to-50000-by-december-31-2026-454-325-222-878-949-487-451-853",
      "curPrice": 0.375,
      "estimatedEdge": 0.0623,
      "kellyBet": 2.49,
      "kellyFull": 0.0997,
      "nSmartTraders": 3,
      "totalTradersChecked": 92,
      "smartTraderNames": [
        "oegdatam",
        "JnStTrdrBnusFnd",
        "justdance"
      ],
      "countSignal": 0.0255,
      "sizeSignal": 1.0,
      "totalExposure": 60976.97,
      "weightedAvgEntry": 0.5565
    },
    {
      "title": "Will J.D. Vance win the 2028 Republican presidential nomination?",
      "outcome": "Yes",
      "slug": "will-jd-vance-win-the-2028-republican-presidential-nomination",
      "url": "https://polymarket.com/event/will-jd-vance-win-the-2028-republican-presidential-nomination",
      "curPrice": 0.3775,
      "estimatedEdge": 0.0605,
      "kellyBet": 2.43,
      "kellyFull": 0.0972,
      "nSmartTraders": 2,
      "totalTradersChecked": 92,
      "smartTraderNames": [
        "debased",
        "humiliating piglet"
      ],
      "countSignal": 0.0058,
      "sizeSignal": 1.0,
      "totalExposure": 261246.99,
      "weightedAvgEntry": 0.5
    },
    {
      "title": "Boston Red Sox vs. New York Yankees",
      "outcome": "Boston Red Sox",
      "slug": "mlb-bos-nyy-2026-06-06",
      "url": "https://polymarket.com/event/mlb-bos-nyy-2026-06-06",
      "curPrice": 0.51,
      "estimatedEdge": 0.0475,
      "kellyBet": 2.42,
      "kellyFull": 0.0969,
      "nSmartTraders": 2,
      "totalTradersChecked": 92,
      "smartTraderNames": [
        "Countryside",
        "ferrariChampions2026"
      ],
      "countSignal": 0.0822,
      "sizeSignal": 1.0,
      "totalExposure": 38523.95,
      "weightedAvgEntry": 0.4804
    },
    {
      "title": "Wimbledon ATP: Andrey Rublev vs Roman Safiullin",
      "outcome": "Roman Safiullin",
      "slug": "atp-rublev-safiull-2026-06-29",
      "url": "https://polymarket.com/event/atp-rublev-safiull-2026-06-29",
      "curPrice": 0.235,
      "estimatedEdge": 0.0692,
      "kellyBet": 2.26,
      "kellyFull": 0.0905,
      "nSmartTraders": 3,
      "totalTradersChecked": 92,
      "smartTraderNames": [
        "ferrariChampions2026",
        "RN1",
        "0x076daa..."
      ],
      "countSignal": 0.1026,
      "sizeSignal": 1.0,
      "totalExposure": 46575.31,
      "weightedAvgEntry": 0.4308
    },
    {
      "title": "Wimbledon ATP: Aleksandar Kovacevic vs Botic van de Zandschulp",
      "outcome": "Aleksandar Kovacevic",
      "slug": "atp-kovacev-zandsch-2026-06-29",
      "url": "https://polymarket.com/event/atp-kovacev-zandsch-2026-06-29",
      "curPrice": 0.215,
      "estimatedEdge": 0.0691,
      "kellyBet": 2.2,
      "kellyFull": 0.0881,
      "nSmartTraders": 2,
      "totalTradersChecked": 92,
      "smartTraderNames": [
        "RN1",
        "ferrariChampions2026"
      ],
      "countSignal": 0.1016,
      "sizeSignal": 1.0,
      "totalExposure": 6310.37,
      "weightedAvgEntry": 0.3415
    },
    {
      "title": "Wimbledon ATP: Emilio Nava vs Ignacio Buse",
      "outcome": "Emilio Nava",
      "slug": "atp-nava-buse-2026-06-29",
      "url": "https://polymarket.com/event/atp-nava-buse-2026-06-29",
      "curPrice": 0.205,
      "estimatedEdge": 0.0691,
      "kellyBet": 2.17,
      "kellyFull": 0.087,
      "nSmartTraders": 2,
      "totalTradersChecked": 92,
      "smartTraderNames": [
        "RN1",
        "ferrariChampions2026"
      ],
      "countSignal": 0.1016,
      "sizeSignal": 1.0,
      "totalExposure": 4233.28,
      "weightedAvgEntry": 0.4362
    },
    {
      "title": "Will 60 ships transit the Strait of Hormuz on any day by June 30, 2026?",
      "outcome": "Yes",
      "slug": "will-60-ships-transit-the-strait-of-hormuz-on-any-day-by-june-30-2026",
      "url": "https://polymarket.com/event/will-60-ships-transit-the-strait-of-hormuz-on-any-day-by-june-30-2026",
      "curPrice": 0.265,
      "estimatedEdge": 0.063,
      "kellyBet": 2.14,
      "kellyFull": 0.0858,
      "nSmartTraders": 2,
      "totalTradersChecked": 92,
      "smartTraderNames": [
        "Valen9",
        "mombil"
      ],
      "countSignal": 0.0338,
      "sizeSignal": 1.0,
      "totalExposure": 3077.0,
      "weightedAvgEntry": 0.4808
    },
    {
      "title": "Brazil vs. Japan: O/U 1.5",
      "outcome": "Under",
      "slug": "fifwc-bra-jpn-2026-06-29-total-1pt5",
      "url": "https://polymarket.com/event/fifwc-bra-jpn-2026-06-29-total-1pt5",
      "curPrice": 0.275,
      "estimatedEdge": 0.0605,
      "kellyBet": 2.08,
      "kellyFull": 0.0834,
      "nSmartTraders": 2,
      "totalTradersChecked": 92,
      "smartTraderNames": [
        "swisstony",
        "wr0ngw4yb3tt0r"
      ],
      "countSignal": 0.0134,
      "sizeSignal": 1.0,
      "totalExposure": 30658.45,
      "weightedAvgEntry": 0.2738
    },
    {
      "title": "Atlanta Braves vs. Chicago White Sox",
      "outcome": "Chicago White Sox",
      "slug": "mlb-atl-cws-2026-06-11",
      "url": "https://polymarket.com/event/mlb-atl-cws-2026-06-11",
      "curPrice": 0.495,
      "estimatedEdge": 0.041,
      "kellyBet": 2.03,
      "kellyFull": 0.0813,
      "nSmartTraders": 3,
      "totalTradersChecked": 92,
      "smartTraderNames": [
        "Sisyphus.",
        "wr0ngw4yb3tt0r",
        "Countryside"
      ],
      "countSignal": 0.0045,
      "sizeSignal": 1.0,
      "totalExposure": 9545.48,
      "weightedAvgEntry": 0.4629
    },
    {
      "title": "Will Marco Rubio win the 2028 Republican presidential nomination?",
      "outcome": "Yes",
      "slug": "will-marco-rubio-win-the-2028-republican-presidential-nomination",
      "url": "https://polymarket.com/event/will-marco-rubio-win-the-2028-republican-presidential-nomination",
      "curPrice": 0.2205,
      "estimatedEdge": 0.0628,
      "kellyBet": 2.02,
      "kellyFull": 0.0806,
      "nSmartTraders": 2,
      "totalTradersChecked": 92,
      "smartTraderNames": [
        "Jsram",
        "mombil"
      ],
      "countSignal": 0.0315,
      "sizeSignal": 1.0,
      "totalExposure": 131728.42,
      "weightedAvgEntry": 0.3277
    },
    {
      "title": "Mojtaba Khamenei seen in public by July 31?",
      "outcome": "Yes",
      "slug": "mojtaba-khamenei-seen-in-public-by-july-31-827",
      "url": "https://polymarket.com/event/mojtaba-khamenei-seen-in-public-by-july-31-827",
      "curPrice": 0.215,
      "estimatedEdge": 0.063,
      "kellyBet": 2.01,
      "kellyFull": 0.0803,
      "nSmartTraders": 2,
      "totalTradersChecked": 92,
      "smartTraderNames": [
        "Valen9",
        "mombil"
      ],
      "countSignal": 0.0338,
      "sizeSignal": 1.0,
      "totalExposure": 3332.64,
      "weightedAvgEntry": 0.2321
    },
    {
      "title": "Will Germany win on 2026-06-29?",
      "outcome": "No",
      "slug": "fifwc-ger-par-2026-06-29-ger",
      "url": "https://polymarket.com/event/fifwc-ger-par-2026-06-29-ger",
      "curPrice": 0.275,
      "estimatedEdge": 0.0578,
      "kellyBet": 1.99,
      "kellyFull": 0.0798,
      "nSmartTraders": 3,
      "totalTradersChecked": 92,
      "smartTraderNames": [
        "BreakTheBank",
        "0x076daa...",
        "swisstony"
      ],
      "countSignal": 0.0177,
      "sizeSignal": 1.0,
      "totalExposure": 132307.79,
      "weightedAvgEntry": 0.2689
    },
    {
      "title": "Will Bitcoin dip to $55,000 by December 31, 2026?",
      "outcome": "No",
      "slug": "will-bitcoin-dip-to-55000-by-december-31-2026-527-627-868-745-188-361-314-673-612-946-821-624-855-557-684-381-884-939-182",
      "url": "https://polymarket.com/event/will-bitcoin-dip-to-55000-by-december-31-2026-527-627-868-745-188-361-314-673-612-946-821-624-855-557-684-381-884-939-182",
      "curPrice": 0.225,
      "estimatedEdge": 0.0616,
      "kellyBet": 1.99,
      "kellyFull": 0.0795,
      "nSmartTraders": 2,
      "totalTradersChecked": 92,
      "smartTraderNames": [
        "JnStTrdrBnusFnd",
        "justdance"
      ],
      "countSignal": 0.0176,
      "sizeSignal": 1.0,
      "totalExposure": 15697.87,
      "weightedAvgEntry": 0.4944
    },
    {
      "title": "US-Iran Final Nuclear Deal by August 18, 2026?",
      "outcome": "Yes",
      "slug": "us-iran-final-nuclear-deal-by-august-18-2026-20260621201255153",
      "url": "https://polymarket.com/event/us-iran-final-nuclear-deal-by-august-18-2026-20260621201255153",
      "curPrice": 0.2,
      "estimatedEdge": 0.0624,
      "kellyBet": 1.95,
      "kellyFull": 0.078,
      "nSmartTraders": 2,
      "totalTradersChecked": 92,
      "smartTraderNames": [
        "debased",
        "Valen9"
      ],
      "countSignal": 0.0267,
      "sizeSignal": 1.0,
      "totalExposure": 1148.52,
      "weightedAvgEntry": 0.2141
    },
    {
      "title": "Will JD Vance win the 2028 US Presidential Election?",
      "outcome": "Yes",
      "slug": "will-jd-vance-win-the-2028-us-presidential-election",
      "url": "https://polymarket.com/event/will-jd-vance-win-the-2028-us-presidential-election",
      "curPrice": 0.1935,
      "estimatedEdge": 0.0622,
      "kellyBet": 1.93,
      "kellyFull": 0.0771,
      "nSmartTraders": 3,
      "totalTradersChecked": 92,
      "smartTraderNames": [
        "superblueinc",
        "poli.monaco",
        "alwayslatetotheparty"
      ],
      "countSignal": 0.0245,
      "sizeSignal": 1.0,
      "totalExposure": 5105.38,
      "weightedAvgEntry": 0.3116
    },
    {
      "title": "Will Brazil vs. Japan end in a draw?",
      "outcome": "Yes",
      "slug": "fifwc-bra-jpn-2026-06-29-draw",
      "url": "https://polymarket.com/event/fifwc-bra-jpn-2026-06-29-draw",
      "curPrice": 0.255,
      "estimatedEdge": 0.0562,
      "kellyBet": 1.88,
      "kellyFull": 0.0754,
      "nSmartTraders": 2,
      "totalTradersChecked": 92,
      "smartTraderNames": [
        "0x076daa...",
        "HBAFlover98"
      ],
      "countSignal": 0.0052,
      "sizeSignal": 1.0,
      "totalExposure": 30138.02,
      "weightedAvgEntry": 0.2479
    },
    {
      "title": "Will Bitcoin dip to $57,500 in June?",
      "outcome": "Yes",
      "slug": "will-bitcoin-dip-to-57pt5k-in-june-2026-623-575",
      "url": "https://polymarket.com/event/will-bitcoin-dip-to-57pt5k-in-june-2026-623-575",
      "curPrice": 0.1395,
      "estimatedEdge": 0.0646,
      "kellyBet": 1.88,
      "kellyFull": 0.0751,
      "nSmartTraders": 2,
      "totalTradersChecked": 92,
      "smartTraderNames": [
        "justdance",
        "0xA0da9371A4Aa5f2eCE33eDa9B6f47b656bAd1F80-1777002339626"
      ],
      "countSignal": 0.0515,
      "sizeSignal": 1.0,
      "totalExposure": 4601.31,
      "weightedAvgEntry": 0.3421
    },
    {
      "title": "Will Spain win the 2026 FIFA World Cup?",
      "outcome": "Yes",
      "slug": "will-spain-win-the-2026-fifa-world-cup-963",
      "url": "https://polymarket.com/event/will-spain-win-the-2026-fifa-world-cup-963",
      "curPrice": 0.1105,
      "estimatedEdge": 0.0666,
      "kellyBet": 1.87,
      "kellyFull": 0.0749,
      "nSmartTraders": 9,
      "totalTradersChecked": 92,
      "smartTraderNames": [
        "Sisyphus.",
        "Jsram",
        "Q96s3kwozynxpau",
        "debased",
        "0x37ee3BCEb4fBf028fb90D1463A4a5354Da02f86F-1781205947489"
      ],
      "countSignal": 0.0734,
      "sizeSignal": 1.0,
      "totalExposure": 184850.74,
      "weightedAvgEntry": 0.1497
    },
    {
      "title": "Will England win the 2026 FIFA World Cup?",
      "outcome": "Yes",
      "slug": "will-england-win-the-2026-fifa-world-cup-937",
      "url": "https://polymarket.com/event/will-england-win-the-2026-fifa-world-cup-937",
      "curPrice": 0.1025,
      "estimatedEdge": 0.0627,
      "kellyBet": 1.75,
      "kellyFull": 0.0699,
      "nSmartTraders": 7,
      "totalTradersChecked": 92,
      "smartTraderNames": [
        "BreakTheBank",
        "Jsram",
        "Countryside",
        "0x37ee3BCEb4fBf028fb90D1463A4a5354Da02f86F-1781205947489",
        "Q96s3kwozynxpau"
      ],
      "countSignal": 0.0534,
      "sizeSignal": 1.0,
      "totalExposure": 559865.2,
      "weightedAvgEntry": 0.0993
    },
    {
      "title": "Will Gavin Newsom win the 2028 US Presidential Election?",
      "outcome": "Yes",
      "slug": "will-gavin-newsom-win-the-2028-us-presidential-election",
      "url": "https://polymarket.com/event/will-gavin-newsom-win-the-2028-us-presidential-election",
      "curPrice": 0.1225,
      "estimatedEdge": 0.0542,
      "kellyBet": 1.54,
      "kellyFull": 0.0617,
      "nSmartTraders": 2,
      "totalTradersChecked": 92,
      "smartTraderNames": [
        "mombil",
        "The Spirit of Ukraine>UMA"
      ],
      "countSignal": 0.0423,
      "sizeSignal": 1.0,
      "totalExposure": 4846.26,
      "weightedAvgEntry": 0.1074
    },
    {
      "title": "Wimbledon ATP: Casper Ruud vs Hubert Hurkacz",
      "outcome": "Casper Ruud",
      "slug": "atp-ruud-hurkacz-2026-06-29",
      "url": "https://polymarket.com/event/atp-ruud-hurkacz-2026-06-29",
      "curPrice": 0.315,
      "estimatedEdge": 0.0407,
      "kellyBet": 1.49,
      "kellyFull": 0.0595,
      "nSmartTraders": 2,
      "totalTradersChecked": 92,
      "smartTraderNames": [
        "ferrariChampions2026",
        "RN1"
      ],
      "countSignal": 0.1016,
      "sizeSignal": 0.5264,
      "totalExposure": 526.39,
      "weightedAvgEntry": 0.3409
    },
    {
      "title": "Will France win the 2026 FIFA World Cup?",
      "outcome": "Yes",
      "slug": "will-france-win-the-2026-fifa-world-cup-924",
      "url": "https://polymarket.com/event/will-france-win-the-2026-fifa-world-cup-924",
      "curPrice": 0.2345,
      "estimatedEdge": 0.0358,
      "kellyBet": 1.17,
      "kellyFull": 0.0468,
      "nSmartTraders": 7,
      "totalTradersChecked": 92,
      "smartTraderNames": [
        "Jsram",
        "debased",
        "bitterfish",
        "0x37ee3BCEb4fBf028fb90D1463A4a5354Da02f86F-1781205947489",
        "Gengfrauds"
      ],
      "countSignal": 0.094,
      "sizeSignal": 1.0,
      "totalExposure": 94604.79,
      "weightedAvgEntry": 0.1868
    },
    {
      "title": "Will Hanwha Life Esports win the LCK 2026 season playoffs?",
      "outcome": "Yes",
      "slug": "will-hanwha-life-esports-win-the-lck-2026-season-playoffs",
      "url": "https://polymarket.com/event/will-hanwha-life-esports-win-the-lck-2026-season-playoffs",
      "curPrice": 0.2075,
      "estimatedEdge": 0.0349,
      "kellyBet": 1.1,
      "kellyFull": 0.0441,
      "nSmartTraders": 2,
      "totalTradersChecked": 92,
      "smartTraderNames": [
        "213546566",
        "Gengfrauds"
      ],
      "countSignal": 0.0336,
      "sizeSignal": 0.5706,
      "totalExposure": 570.6,
      "weightedAvgEntry": 0.2012
    }
  ]
}